LICENSE
README.md
setup.cfg
setup.py
.idea/misc.xml
.idea/modules.xml
.idea/pytest-playwright1.iml
.idea/vcs.xml
.idea/inspectionProfiles/Project_Default.xml
.idea/inspectionProfiles/profiles_settings.xml
pytest_playwright/__init__.py
pytest_playwright/_repo_version.py
pytest_playwright/pytest_playwright.py
pytest_playwrights.egg-info/PKG-INFO
pytest_playwrights.egg-info/SOURCES.txt
pytest_playwrights.egg-info/dependency_links.txt
pytest_playwrights.egg-info/entry_points.txt
pytest_playwrights.egg-info/requires.txt
pytest_playwrights.egg-info/top_level.txt