Metadata-Version: 2.1
Name: pytest-playwrights
Version: 0.0.5
Summary: A pytest wrapper with fixtures for Playwright to automate web browsers
Home-page: https://github.com/939449414/pytest-playwrights.git
Author: liuxiankun
Author-email: 939449414@qq.com
License: UNKNOWN
Platform: UNKNOWN
Classifier: Programming Language :: Python :: 3
Classifier: Programming Language :: Python :: 3.7
Classifier: Programming Language :: Python :: 3.8
Classifier: Programming Language :: Python :: 3.9
Classifier: Programming Language :: Python :: 3.10
Classifier: License :: OSI Approved :: Apache Software License
Classifier: Operating System :: OS Independent
Classifier: Framework :: Pytest
Requires-Python: >=3.7
License-File: LICENSE
